{
  "type": "FeatureCollection",
  "features": [
    {
      "geometry": {
        "type": "Point",
        "coordinates": [
          -73.08062821626663,
          -36.778436547945105
        ]
      },
      "type": "Feature",
      "properties": {
        "fono": 696969,
        "cargo": "Actor Porno1",
        "foto": "/media/avatar/jhonnysins_BAdYgjs.jpg",
        "nivel_riesgo": 1,
        "nombre_emergencia": "Tetis",
        "nro_emergencia": "123456",
        "nombre": "Jhonny Sins",
        "id": null,
        "tipo_contacto": "POLOLO"
      }
    },
    {
      "geometry": {
        "type": "Point",
        "coordinates": [
          -73.08110564947128,
          -36.77808636879467
        ]
      },
      "type": "Feature",
      "properties": {
        "fono": 696969,
        "cargo": "Actor Porno3",
        "foto": "/media/avatar/jhonnysins_BAdYgjs.jpg",
        "nivel_riesgo": 4,
        "nombre_emergencia": "Tetis",
        "nro_emergencia": "123456",
        "nombre": "Jhonny Sins",
        "id": null,
        "tipo_contacto": "POLOLO"
      }
    },
    {
      "geometry": {
        "type": "Point",
        "coordinates": [
          -73.08115124702454,
          -36.77833557620697
        ]
      },
      "type": "Feature",
      "properties": {
        "fono": 696969,
        "cargo": "Actor Porno2",
        "foto": "/media/avatar/jhonnysins_BAdYgjs.jpg",
        "nivel_riesgo": 5,
        "nombre_emergencia": "Tetis",
        "nro_emergencia": "123456",
        "nombre": "Jhonny Sins",
        "id": null,
        "tipo_contacto": "POLOLO"
      }
    }
  ]
}