{"crs": {"type": "link", "properties": {"href": "http://spatialreference.org/ref/epsg/4326/", "type": "proj4"}}, "type": "FeatureCollection", "features": [{"geometry": {"type": "Point", "coordinates": [-73.08097277777777, -36.77828222222222]}, "type": "Feature", "properties": {"fono": 696969, "cargo": "Actor Porno", "foto": "/media/avatar/jhonnysins_BAdYgjs.jpg", "nivel_riesgo": 5, "nombre_emergencia": "Tetis", "nro_emergencia": "123456", "nombre": "Jhonny Sins", "id": null, "tipo_contacto": "POLOLO"}}]}